{
    "created_time": "2018-07-20T14:08:05Z",
    "files": [
        {
            "attachment_folder": "",
            "attachments": [
            ],
            "created_time": "2018-07-20T14:08:54Z",
            "modified_time": "2018-07-20T14:08:54Z",
            "name": "第二章 C语言概述.md"
        },
        {
            "attachment_folder": "",
            "attachments": [
            ],
            "created_time": "2018-08-13T13:26:32Z",
            "modified_time": "2018-08-13T13:26:32Z",
            "name": "第三章 数据和C.md"
        }
    ],
    "sub_directories": [
    ],
    "version": "1"
}
